{
  "framerate": "24",
  "images": [
    "spriteSheets/sheet_standing-ipad.png"
  ],
  "frames": [
    [
      1666,
      1187,
      311,
      411,
      0,
      294,
      190
    ],
    [
      1666,
      1187,
      311,
      411,
      0,
      294,
      190
    ],
    [
      0,
      790,
      310,
      396,
      0,
      293,
      190
    ],
    [
      403,
      1187,
      310,
      398,
      0,
      293,
      192
    ],
    [
      713,
      1187,
      313,
      398,
      0,
      296,
      192
    ],
    [
      713,
      1187,
      313,
      398,
      0,
      296,
      192
    ],
    [
      1346,
      1187,
      320,
      399,
      0,
      303,
      193
    ],
    [
      1346,
      1187,
      320,
      399,
      0,
      303,
      193
    ],
    [
      1026,
      1187,
      320,
      399,
      0,
      303,
      193
    ],
    [
      1319,
      790,
      320,
      397,
      0,
      303,
      191
    ],
    [
      65,
      1187,
      338,
      397,
      0,
      321,
      191
    ],
    [
      1639,
      790,
      338,
      397,
      0,
      321,
      191
    ],
    [
      982,
      790,
      337,
      396,
      0,
      320,
      190
    ],
    [
      645,
      790,
      337,
      396,
      0,
      320,
      190
    ],
    [
      310,
      790,
      335,
      396,
      0,
      318,
      190
    ],
    [
      686,
      394,
      335,
      394,
      0,
      318,
      188
    ],
    [
      352,
      394,
      334,
      394,
      0,
      317,
      188
    ],
    [
      352,
      394,
      334,
      394,
      0,
      317,
      188
    ],
    [
      1348,
      0,
      315,
      393,
      0,
      298,
      187
    ],
    [
      1348,
      0,
      315,
      393,
      0,
      298,
      187
    ],
    [
      1034,
      0,
      314,
      393,
      0,
      297,
      187
    ],
    [
      1663,
      0,
      314,
      394,
      0,
      297,
      188
    ],
    [
      35,
      394,
      317,
      394,
      0,
      300,
      188
    ],
    [
      35,
      394,
      317,
      394,
      0,
      300,
      188
    ],
    [
      705,
      0,
      329,
      391,
      0,
      312,
      185
    ],
    [
      705,
      0,
      329,
      391,
      0,
      312,
      185
    ],
    [
      378,
      0,
      327,
      391,
      0,
      310,
      185
    ],
    [
      1341,
      394,
      327,
      395,
      0,
      310,
      189
    ],
    [
      1021,
      394,
      320,
      395,
      0,
      303,
      189
    ],
    [
      1021,
      394,
      320,
      395,
      0,
      303,
      189
    ],
    [
      1668,
      394,
      309,
      396,
      0,
      292,
      190
    ],
    [
      1668,
      394,
      309,
      396,
      0,
      292,
      190
    ]
  ],
  "animations": {
    "Standing": [
      0,
      31
    ]
  }
}